codicent_py-1.3.5.dist-info/licenses/LICENSE
codicentpy/__init__.py
codicentpy/core.py
codicentpy/test_codicent.py
codicent_py-1.3.5.dist-info/METADATA
codicent_py-1.3.5.dist-info/WHEEL
codicent_py-1.3.5.dist-info/top_level.txt
codicent_py-1.3.5.dist-info/RECORD
