Metadata-Version: 2.4
Name: codicent-py
Version: 1.3.5
Summary: Python interface to the Codicent API
Home-page: https://github.com/izaxon/codicent-py
Author: Johan
Author-email: Johan <johan@example.com>
License: MIT
Project-URL: Homepage, https://github.com/izaxon/codicent-py
Project-URL: Repository, https://github.com/izaxon/codicent-py
Project-URL: Issues, https://github.com/izaxon/codicent-py/issues
Keywords: codicent,api,client
Classifier: Development Status :: 4 - Beta
Classifier: Intended Audience :: Developers
Classifier: License :: OSI Approved :: MIT License
Classifier: Operating System :: OS Independent
Classifier: Programming Language :: Python :: 3
Classifier: Programming Language :: Python :: 3.7
Classifier: Programming Language :: Python :: 3.8
Classifier: Programming Language :: Python :: 3.9
Classifier: Programming Language :: Python :: 3.10
Classifier: Programming Language :: Python :: 3.11
Classifier: Programming Language :: Python :: 3.12
Requires-Python: >=3.7
License-File: LICENSE
Requires-Dist: requests>=2.25.0
Dynamic: author
Dynamic: home-page
Dynamic: license-file
Dynamic: requires-python
